[
  {
    "id": 1,
    "type": "radio",
    "question": "한번 식사할 때 김치를 제외한 채소류, 해조류, 버섯 등으로 만든 반찬을 몇 가지나 드십니까?",
    "options": ["거의 먹지 않는다", "1가지", "2가지", "3가지", "4가지"]
  },
  {
    "id": 2,
    "type": "radio",
    "question": "과일을 얼마나 자주 드십니까?",
    "options": ["거의 먹지 않는다", "2주일에 1번", "일주일에 1~3번", "일주일에 4~6번", "하루에 1번 이상"]
  },
  {
    "id": 3,
    "type": "radio",
    "question": "우유나 유제품(치즈, 무가당 요거트)을 얼마나 자주 드십니까?",
    "options": ["2주일에 1번 이하", "일주일에 1~3번", "일주일에 4~6번", "하루에 1번", "하루에 2번 이상"]
  },
  {
    "id": 4,
    "type": "radio",
    "question": "전곡이나 곡류(현미밥, 잡곡밥, 통밀빵, 국수, 감자, 고구마 등)를 얼마나 자주 드십니까?",
    "options": ["거의 먹지 않는다", "일주일에 1~3번", "일주일에 4~6번", "하루에 1번", "하루에 2번 이상"]
  },
  {
    "id": 5,
    "type": "radio",
    "question": "콩이나 두부를 얼마나 자주 드십니까?",
    "options": ["2주일에 1번 이하", "일주일에 1~3번", "일주일에 4~6번", "하루에 1번", "하루에 2번 이상"]
  },
  {
    "id": 6,
    "type": "radio",
    "question": "달걀(메추리알 등)을 얼마나 자주 드십니까?",
    "options": ["거의 먹지 않는다", "2주일에 1번", "일주일에 1~3번", "일주일에 4~6번", "하루에 1번 이상"]
  },
  {
    "id": 7,
    "type": "radio",
    "question": "생선류를 얼마나 자주 드십니까?",
    "options": ["거의 먹지 않는다", "2주일에 1번", "일주일에 1~3번", "일주일에 4~6번", "하루에 1번 이상"]
  },
  {
    "id": 8,
    "type": "radio",
    "question": "피자, 햄버거, 치킨 등의 패스트푸드를 얼마나 자주 드십니까?",
    "options": ["거의 먹지 않는다", "2주일에 1번", "일주일에 1~3번", "일주일에 4~6번", "하루에 1번 이상"]
  },
  {
    "id": 9,
    "type": "radio",
    "question": "맵고 짠 국물음식(라면, 찌개류, 탕류, 국물 떡볶이 등)을 얼마나 자주 드십니까?",
    "options": ["2주일에 1번 이하", "일주일에 1~3번", "일주일에 4~6번", "하루에 1번", "하루에 2번 이상"]
  },
  {
    "id": 10,
    "type": "radio",
    "question": "평소에 삼겹살, 햄, 소시지, 베이컨 등 기름기가 많은 가공식품 및 기름진 고기를 얼마나 자주 드십니까?",
    "options": ["거의 먹지 않는다", "2주일에 1번", "일주일에 1~3번", "일주일에 4~6번", "하루에 1번 이상"]
  },
  {
    "id": 11,
    "type": "radio",
    "question": "과식이나 폭식을 얼마나 자주 드십니까?\n* 과식: 필요량 이상으로 음식물을 섭취함",
    "options": ["거의 하지 않는다", "한달에 1번", "2주일에 1번", "일주일에 1번", "일주일에 3~4번", "하루에 1번 이상"]
  },
  {
    "id": 12,
    "type": "radio",
    "question": "일주일 동안 아침식사를 얼마나 자주 하십니까?",
    "options": ["거의 먹지 않는다", "일주일에 1~2번", "일주일에 3~4번", "일주일에 5~6번", "매일"]
  },
  {
    "id": 13,
    "type": "radio",
    "question": "평소에 건강에 좋은 식생활을 하려고 노력하십니까?",
    "options": ["전혀 노력하지 않는다", "노력하지 않는 편이다", "보통이다", "노력하는 편이다", "매우 노력한다"]
  },
  {
    "id": 14,
    "type": "radio",
    "question": "음식을 먹기 전에 손을 씻으십니까?",
    "options": ["전혀 씻지 않는다", "씻지 않는 편이다", "보통이다", "씻는 편이다", "항상 씻는다"]
  },
  {
    "id": 15,
    "type": "radio",
    "question": "1회 섭취량 기준으로 남자의 경우 7잔(또는 맥주 5캔), 여자의 경우 5잔(또는 맥주 3캔) 이상의 술을 얼마나 자주 드십니까?",
    "options": ["최근 1년간 전혀 마시지 않았다", "한달에 1번 미만", "한달에 1번 정도", "한달에 2~4번", "일주일에 2~3번 정도", "일주일에 4번 이상"]
  },
  {
    "id": 16,
    "type": "radio",
    "question": "30분 이상 숨이 찰 정도의 운동을 얼마나 자주 하십니까?",
    "options": ["거의 하지 않는다", "일주일에 1~2번", "일주일에 3~4번", "일주일에 5~6번", "매일"]
  },
  {
    "id": 17,
    "type": "checkbox",
    "question": "현재 드시고 계신 영양제 및 건강기능식품이 있으십니까? (복수선택가능)",
    "options": ["멀티비타민", "밀크씨슬", "루테인", "테아닌", "오메가3", "홍삼", "프로바이오틱스", "피부미용(콜라겐, 코엔자임Q10, 프로폴리스, 히알루론산)", "연골(칼슘, N-아세틸글루코사민)", "없음"]
  }
]